fewsats_mcp/__init__.py
fewsats_mcp/server.py
fewsats_mcp-0.1.7.dist-info/METADATA
fewsats_mcp-0.1.7.dist-info/WHEEL
fewsats_mcp-0.1.7.dist-info/entry_points.txt
fewsats_mcp-0.1.7.dist-info/RECORD
