Metadata-Version: 2.4
Name: fewsats-mcp
Version: 0.1.7
Summary: Fewsats MCP server
Requires-Python: >=3.10
Requires-Dist: fewsats>=0.0.22
Requires-Dist: mcp>=1.10.1
